<?xml version="1.0" encoding="utf-8" ?>
<dwsync>
<file name="Armorun.html" server="ftp.membres.lycos.fr" local="125555796000000000" remote="125555796000000000" />
<file name="breastplate.gif" server="ftp.membres.lycos.fr" local="125555796000000000" remote="125555796000000000" />
<file name="chainmail.gif" server="ftp.membres.lycos.fr" local="125555796000000000" remote="125555796000000000" />
<file name="fullplate.gif" server="ftp.membres.lycos.fr" local="125555796000000000" remote="125555796000000000" />
<file name="leatherarmor.gif" server="ftp.membres.lycos.fr" local="125555796000000000" remote="125555796000000000" />
<file name="najslightplate.gif" server="ftp.membres.lycos.fr" local="125555796000000000" remote="125555796000000000" />
<file name="studleather.gif" server="ftp.membres.lycos.fr" local="125555796000000000" remote="125555796000000000" />
<file name="tornfleshofsouls.gif" server="ftp.membres.lycos.fr" local="125555796000000000" remote="125555796000000000" />
<file name="valor.gif" server="ftp.membres.lycos.fr" local="125555796000000000" remote="125555796000000000" />
<file name="wisdomswrap.gif" server="ftp.membres.lycos.fr" local="125555796000000000" remote="125555796000000000" />
</dwsync>